AlphavantageLFT/Alphavantage.py
AlphavantageLFT/AlphavantageLFT.py
AlphavantageLFT/__init__.py
AlphavantageLFT-0.0.40.dist-info/LICENSE
AlphavantageLFT-0.0.40.dist-info/METADATA
AlphavantageLFT-0.0.40.dist-info/WHEEL
AlphavantageLFT-0.0.40.dist-info/top_level.txt
AlphavantageLFT-0.0.40.dist-info/RECORD
